{
    "1": {
        "name": "下九流"
    },
    "2": {
        "name": "下九流"
    },
    "3": {
        "name": "下九流"
    },
    "4": {
        "name": "农户"
    },
    "5": {
        "name": "病乞丐"
    },
    "6": {
        "name": "小毛贼"
    },
    "7": {
        "name": "地痞"
    },
    "8": {
        "name": "亡命徒"
    },
    "9": {
        "name": "狐媚子"
    },
    "10": {
        "name": "鬼仆"
    },
    "11": {
        "name": "妖乐师"
    },
    "12": {
        "name": "异疆怪人"
    },
    "13": {
        "name": "丧心侠士"
    },
    "14": {
        "name": "疯魔"
    },
    "15": {
        "name": "绝境客"
    },
    "16": {
        "name": "乞丐"
    },
    "17": {
        "name": "手艺人"
    },
    "18": {
        "name": "大夫"
    },
    "19": {
        "name": "商人"
    },
    "20": {
        "name": "文人"
    },
    "21": {
        "name": "豪富"
    },
    "22": {
        "name": "权贵"
    },
    "23": {
        "name": "城主"
    },
    "24": {
        "name": "乞丐"
    },
    "25": {
        "name": "农户"
    },
    "26": {
        "name": "手艺人"
    },
    "27": {
        "name": "大夫"
    },
    "28": {
        "name": "商人"
    },
    "29": {
        "name": "文人"
    },
    "30": {
        "name": "豪富"
    },
    "31": {
        "name": "权贵"
    },
    "32": {
        "name": "村长"
    },
    "33": {
        "name": "乞丐"
    },
    "34": {
        "name": "手艺人"
    },
    "35": {
        "name": "大夫"
    },
    "36": {
        "name": "商人"
    },
    "37": {
        "name": "文人"
    },
    "38": {
        "name": "豪富"
    },
    "39": {
        "name": "权贵"
    },
    "40": {
        "name": "镇长"
    },
    "41": {
        "name": "乞丐"
    },
    "42": {
        "name": "手艺人"
    },
    "43": {
        "name": "大夫"
    },
    "44": {
        "name": "商人"
    },
    "45": {
        "name": "文人"
    },
    "46": {
        "name": "豪富"
    },
    "47": {
        "name": "二当家"
    },
    "48": {
        "name": "大当家"
    },
    "49": {
        "name": "太乙百子"
    }
}
